jacobi/__init__.py
jacobi/_jacobi.py
jacobi/_propagate.py
jacobi/_typing.py
jacobi/_version.py
jacobi-0.9.2.dist-info/LICENSE
jacobi-0.9.2.dist-info/METADATA
jacobi-0.9.2.dist-info/WHEEL
jacobi-0.9.2.dist-info/top_level.txt
jacobi-0.9.2.dist-info/RECORD
