Metadata-Version: 2.1
Name: jacobi
Version: 0.9.2
Summary: Compute numerical derivatives
Author: Hans Dembinski
Author-email: hans.dembinski@gmail.com
License: Copyright 2020 Hans Dembinski
Project-URL: repository, https://github.com/hdembinski/jacobi
Project-URL: documentation, https://hdembinski.github.io/jacobi/
Classifier: Development Status :: 4 - Beta
Classifier: License :: OSI Approved :: MIT License
Classifier: Programming Language :: Python :: 3
Classifier: Operating System :: OS Independent
Classifier: Operating System :: POSIX :: Linux
Classifier: Operating System :: MacOS
Classifier: Operating System :: Microsoft :: Windows
Classifier: Topic :: Scientific/Engineering
Requires-Python: >=3.8
Provides-Extra: test
Provides-Extra: doc
Provides-Extra: plot
License-File: LICENSE
